md_live/__init__.py
md_live/__main__.py
md_live/cli.py
md_live/md_live.py
md_live/utils.py
md_live-0.1.0.dist-info/licenses/LICENSE
md_live-0.1.0.dist-info/METADATA
md_live-0.1.0.dist-info/WHEEL
md_live-0.1.0.dist-info/entry_points.txt
md_live-0.1.0.dist-info/top_level.txt
md_live-0.1.0.dist-info/RECORD
