Metadata-Version: 2.4
Name: md-live
Version: 0.1.0
Summary: md-live is Markdown with live executed code blocks
Author-email: "Audrey M. Roy Greenfeld" <audrey@feldroy.com>
Maintainer-email: "Audrey M. Roy Greenfeld" <audrey@feldroy.com>
License: MIT
Project-URL: bugs, https://github.com/audreyfeldroy/md_live/issues
Project-URL: changelog, https://github.com/audreyfeldroy/md_live/blob/master/changelog.md
Project-URL: homepage, https://github.com/audreyfeldroy/md_live
Requires-Python: >=3.10
License-File: LICENSE
Requires-Dist: typer
Provides-Extra: test
Requires-Dist: coverage; extra == "test"
Requires-Dist: pytest; extra == "test"
Requires-Dist: ruff; extra == "test"
Requires-Dist: ty; extra == "test"
Requires-Dist: ipdb; extra == "test"
Dynamic: license-file
